{"openapi":"3.1.0","info":{"title":"FastAPI","version":"0.1.0"},"paths":{"/init_csv":{"get":{"summary":"Init Csv","operationId":"init_csv_init_csv_get","responses":{"200":{"description":"Successful Response","content":{"application/json":{"schema":{"type":"string","title":"Response Init Csv Init Csv Get"}}}}}}},"/search":{"get":{"summary":"Search","operationId":"search_search_get","parameters":[{"name":"search_query","in":"query","required":false,"schema":{"anyOf":[{"type":"string"},{"type":"null"}],"title":"Search Query"}}],"responses":{"200":{"description":"Successful Response","content":{"application/json":{"schema":{"type":"array","items":{"type":"object"},"title":"Response Search Search Get"}}}},"422":{"description":"Validation Error","content":{"application/json":{"schema":{"$ref":"#/components/schemas/HTTPValidationError"}}}}}}},"/remove":{"get":{"summary":"Remover","operationId":"remover_remove_get","parameters":[{"name":"id","in":"query","required":false,"schema":{"anyOf":[{"type":"integer"},{"type":"null"}],"title":"Id"}}],"responses":{"200":{"description":"Successful Response","content":{"application/json":{"schema":{"type":"string","title":"Response Remover Remove Get"}}}},"422":{"description":"Validation Error","content":{"application/json":{"schema":{"$ref":"#/components/schemas/HTTPValidationError"}}}}}}}},"components":{"schemas":{"HTTPValidationError":{"properties":{"detail":{"items":{"$ref":"#/components/schemas/ValidationError"},"type":"array","title":"Detail"}},"type":"object","title":"HTTPValidationError"},"ValidationError":{"properties":{"loc":{"items":{"anyOf":[{"type":"string"},{"type":"integer"}]},"type":"array","title":"Location"},"msg":{"type":"string","title":"Message"},"type":{"type":"string","title":"Error Type"}},"type":"object","required":["loc","msg","type"],"title":"ValidationError"}}}}